myURcontrol/__init__.py
myURcontrol/myURcontrol.py
myURcontrol-1.0.1.dist-info/METADATA
myURcontrol-1.0.1.dist-info/WHEEL
myURcontrol-1.0.1.dist-info/top_level.txt
myURcontrol-1.0.1.dist-info/RECORD
