Metadata-Version: 2.1
Name: myURcontrol
Version: 1.0.1
Summary: For UR control
Author: Toshihiro Nishimura
Author-email: tnishimura@se.kanazawa-u.ac.jp
License: MIT
Requires-Dist: numpy
Requires-Dist: scipy
